CHANGES
MANIFEST.in
README
setup.cfg
setup.py
sphinxcontrib/__init__.py
sphinxcontrib/smblink.py
sphinxcontrib/smblink_test.py
sphinxcontrib_smblink.egg-info/PKG-INFO
sphinxcontrib_smblink.egg-info/SOURCES.txt
sphinxcontrib_smblink.egg-info/dependency_links.txt
sphinxcontrib_smblink.egg-info/namespace_packages.txt
sphinxcontrib_smblink.egg-info/not-zip-safe
sphinxcontrib_smblink.egg-info/requires.txt
sphinxcontrib_smblink.egg-info/top_level.txt