Metadata-Version: 1.0
Name: sphinxcontrib-smblink
Version: 0.2
Summary: Sphinx Windows Share Links (WSL) role extension
Home-page: https://github.com/goingmywaynet/sphinxcontrib-smblink.git
Author: Joey Chen
Author-email: joey-tech@goingmyway.net
License: BSD
Keywords: sphinx,sphinxcontrib,smb,windows,link,share
Platform: any
Classifier: Development Status :: 3 - Alpha
Classifier: Environment :: Console
Classifier: Environment :: Web Environment
Classifier: Intended Audience :: Developers
Classifier: License :: OSI Approved :: BSD License
Classifier: Natural Language :: Japanese
Classifier: Operating System :: Microsoft :: Windows
Classifier: Programming Language :: Python
Classifier: Topic :: Documentation
Classifier: Topic :: Utilities
